{
  "id": 469,
  "name": "Yanmega",
  "height": 19,
  "weight": 515,
  "base_experience": 180,
  "types": [
    "bug",
    "flying"
  ],
  "abilities": [
    {
      "name": "speed-boost",
      "is_hidden": false
    },
    {
      "name": "tinted-lens",
      "is_hidden": false
    },
    {
      "name": "frisk",
      "is_hidden": true
    }
  ],
  "stats": {
    "hp": 86,
    "attack": 76,
    "defense": 86,
    "special-attack": 116,
    "special-defense": 56,
    "speed": 95
  },
  "images": {
    "front_default": "https://raw.githubusercontent.com/PokeAPI/sprites/master/sprites/pokemon/469.png",
    "front_shiny": "https://raw.githubusercontent.com/PokeAPI/sprites/master/sprites/pokemon/shiny/469.png",
    "official_artwork": "https://raw.githubusercontent.com/PokeAPI/sprites/master/sprites/pokemon/other/official-artwork/469.png"
  },
  "color": "green",
  "generation": 4,
  "descriptions": {
    "en": "By churning its wings, it creates shock waves that inflict critical internal injuries to foes.",
    "es": "Su técnica favorita consiste en volar a gran velocidad y despedazar con su mandíbula a su oponente en un instante.",
    "ca": "Agitant les seves ales, crea ones de xoc que infligeixen greus danys interns als seus rivals."
  },
  "names": {
    "en": "Yanmega",
    "es": "PENDING_TRANSLATION",
    "ca": "Yanmega"
  }
}