{
  "id": 298,
  "name": "Azurill",
  "height": 2,
  "weight": 20,
  "base_experience": 38,
  "types": [
    "normal",
    "fairy"
  ],
  "abilities": [
    {
      "name": "thick-fat",
      "is_hidden": false
    },
    {
      "name": "huge-power",
      "is_hidden": false
    },
    {
      "name": "sap-sipper",
      "is_hidden": true
    }
  ],
  "stats": {
    "hp": 50,
    "attack": 20,
    "defense": 40,
    "special-attack": 20,
    "special-defense": 40,
    "speed": 20
  },
  "images": {
    "front_default": "https://raw.githubusercontent.com/PokeAPI/sprites/master/sprites/pokemon/298.png",
    "front_shiny": "https://raw.githubusercontent.com/PokeAPI/sprites/master/sprites/pokemon/shiny/298.png",
    "official_artwork": "https://raw.githubusercontent.com/PokeAPI/sprites/master/sprites/pokemon/other/official-artwork/298.png"
  },
  "color": "blue",
  "generation": 3,
  "descriptions": {
    "en": "A Pokémon that lives by water. It moves quickly on land by bouncing on its big tail.",
    "es": "Vive cerca del agua. En la tierra se mueve muy rápido botando sobre su gran cola.",
    "ca": "Un Pokémon que viu a prop de l'aigua. Es mou ràpidament per terra saltant amb la seva gran cua."
  },
  "names": {
    "en": "Azurill",
    "es": "PENDING_TRANSLATION",
    "ca": "Azurill"
  }
}