{
  "id": 921,
  "name": "Pawmi",
  "height": 3,
  "weight": 25,
  "base_experience": 48,
  "types": [
    "electric"
  ],
  "abilities": [
    {
      "name": "static",
      "is_hidden": false
    },
    {
      "name": "natural-cure",
      "is_hidden": false
    },
    {
      "name": "iron-fist",
      "is_hidden": true
    }
  ],
  "stats": {
    "hp": 45,
    "attack": 50,
    "defense": 20,
    "special-attack": 40,
    "special-defense": 25,
    "speed": 60
  },
  "images": {
    "front_default": "https://raw.githubusercontent.com/PokeAPI/sprites/master/sprites/pokemon/921.png",
    "front_shiny": "https://raw.githubusercontent.com/PokeAPI/sprites/master/sprites/pokemon/shiny/921.png",
    "official_artwork": "https://raw.githubusercontent.com/PokeAPI/sprites/master/sprites/pokemon/other/official-artwork/921.png"
  },
  "color": "yellow",
  "generation": 9,
  "descriptions": {
    "en": "It has underdeveloped electric sacs on its cheeks. These sacs can produce electricity only if Pawmi rubs them furiously with the pads on its forepaws.",
    "es": "",
    "ca": "Té unes bosses elèctriques poc desenvolupades a les galtes. Aquestes bosses només poden produir electricitat si el Pawmi les frota frenèticament amb les planxes de les seves potes davanteres."
  },
  "names": {
    "en": "Pawmi",
    "es": "PENDING_TRANSLATION",
    "ca": "Pawmi"
  }
}