{
  "id": 366,
  "name": "Clamperl",
  "height": 4,
  "weight": 525,
  "base_experience": 69,
  "types": [
    "water"
  ],
  "abilities": [
    {
      "name": "shell-armor",
      "is_hidden": false
    },
    {
      "name": "rattled",
      "is_hidden": true
    }
  ],
  "stats": {
    "hp": 35,
    "attack": 64,
    "defense": 85,
    "special-attack": 74,
    "special-defense": 55,
    "speed": 32
  },
  "images": {
    "front_default": "https://raw.githubusercontent.com/PokeAPI/sprites/master/sprites/pokemon/366.png",
    "front_shiny": "https://raw.githubusercontent.com/PokeAPI/sprites/master/sprites/pokemon/shiny/366.png",
    "official_artwork": "https://raw.githubusercontent.com/PokeAPI/sprites/master/sprites/pokemon/other/official-artwork/366.png"
  },
  "color": "blue",
  "generation": 3,
  "descriptions": {
    "en": "CLAMPERL’s sturdy shell is not only good for protection - it is also used for clamping and catching prey. A fully grown CLAMPERL’s shell will be scored with nicks and scratches all over.",
    "es": "Produce durante su vida una sola perla que aumenta los poderes psíquicos al evolucionar.",
    "ca": "El robust capell de CLAMPERL no només serveix per a protegir-se, sinó que també s'utilitza per agafar i atrapar preses. El capell d'un CLAMPERL adult tindrà marques i esgarrapades per tot arreu."
  },
  "names": {
    "en": "Clamperl",
    "es": "Clamperl",
    "ca": "Clamperl"
  },
  "evolution": [
    {
      "id": 366,
      "name": "Clamperl",
      "image_url": "https://raw.githubusercontent.com/PokeAPI/sprites/master/sprites/pokemon/366.png"
    },
    {
      "id": 367,
      "name": "Huntail",
      "image_url": "https://raw.githubusercontent.com/PokeAPI/sprites/master/sprites/pokemon/367.png"
    },
    {
      "id": 368,
      "name": "Gorebyss",
      "image_url": "https://raw.githubusercontent.com/PokeAPI/sprites/master/sprites/pokemon/368.png"
    }
  ],
  "is_legendary": false,
  "is_mythical": false
}