{
  "id": 487,
  "name": "Giratina-Altered",
  "height": 45,
  "weight": 7500,
  "base_experience": 306,
  "types": [
    "ghost",
    "dragon"
  ],
  "abilities": [
    {
      "name": "pressure",
      "is_hidden": false
    },
    {
      "name": "telepathy",
      "is_hidden": true
    }
  ],
  "stats": {
    "hp": 150,
    "attack": 100,
    "defense": 120,
    "special-attack": 100,
    "special-defense": 120,
    "speed": 90
  },
  "images": {
    "front_default": "https://raw.githubusercontent.com/PokeAPI/sprites/master/sprites/pokemon/487.png",
    "front_shiny": "https://raw.githubusercontent.com/PokeAPI/sprites/master/sprites/pokemon/shiny/487.png",
    "official_artwork": "https://raw.githubusercontent.com/PokeAPI/sprites/master/sprites/pokemon/other/official-artwork/487.png"
  },
  "color": "black",
  "generation": 4,
  "descriptions": {
    "en": "A Pokémon that is said to live in a world on the reverse side of ours. It appears in an ancient cemetery.",
    "es": "Vive en el Mundo Distorsión, un mundo opuesto al nuestro y cuyas leyes desafían el sentido común.",
    "ca": "Un Pokémon que es diu que viu en un món a la banda oposada del nostre. Apareix en un antic cementiri."
  },
  "names": {
    "en": "Giratina",
    "es": "Giratina",
    "ca": "Giratina"
  },
  "evolution": null,
  "is_legendary": true,
  "is_mythical": false
}