{
  "id": 550,
  "name": "Basculin-Red-Striped",
  "height": 10,
  "weight": 180,
  "types": [
    "water"
  ],
  "image_url": "https://raw.githubusercontent.com/PokeAPI/sprites/master/sprites/pokemon/550.png",
  "stats": {
    "hp": 70,
    "attack": 92,
    "defense": 65,
    "special-attack": 80,
    "special-defense": 55,
    "speed": 98
  },
  "evolution": [
    {
      "id": 550,
      "name": "Basculin",
      "image_url": "https://raw.githubusercontent.com/PokeAPI/sprites/master/sprites/pokemon/550.png"
    },
    {
      "id": 902,
      "name": "Basculegion",
      "image_url": "https://raw.githubusercontent.com/PokeAPI/sprites/master/sprites/pokemon/902.png"
    }
  ],
  "color": "green",
  "description": "Los de color azul y los de color rojo siempre se pelean. Son muy violentos, pero su sabor es excepcional.",
  "description_catalan": "Els Basculins vermells i blaus no es porten gens bé, i començaran a lluitar de seguida. Aquests Pokémon són molt hostils."
}