{
  "id": 596,
  "name": "Galvantula",
  "height": 8,
  "weight": 143,
  "types": [
    "bug",
    "electric"
  ],
  "image_url": "https://raw.githubusercontent.com/PokeAPI/sprites/master/sprites/pokemon/596.png",
  "stats": {
    "hp": 70,
    "attack": 77,
    "defense": 60,
    "special-attack": 97,
    "special-defense": 60,
    "speed": 108
  },
  "evolution": [
    {
      "id": 595,
      "name": "Joltik",
      "image_url": "https://raw.githubusercontent.com/PokeAPI/sprites/master/sprites/pokemon/595.png"
    },
    {
      "id": 596,
      "name": "Galvantula",
      "image_url": "https://raw.githubusercontent.com/PokeAPI/sprites/master/sprites/pokemon/596.png"
    }
  ],
  "color": "yellow",
  "description": "Pone trampas con hilos electrificados. De este modo, electrocuta a sus enemigos y los inmoviliza por completo.",
  "description_catalan": "Descripció en català per al Pokémon #596. [Traducció pendent]"
}