{
  "id": 330,
  "name": "Flygon",
  "height": 20,
  "weight": 820,
  "types": [
    "ground",
    "dragon"
  ],
  "image_url": "https://raw.githubusercontent.com/PokeAPI/sprites/master/sprites/pokemon/330.png",
  "stats": {
    "hp": 80,
    "attack": 100,
    "defense": 80,
    "special-attack": 80,
    "special-defense": 80,
    "speed": 100
  },
  "evolution": [
    {
      "id": 328,
      "name": "Trapinch",
      "image_url": "https://raw.githubusercontent.com/PokeAPI/sprites/master/sprites/pokemon/328.png"
    },
    {
      "id": 329,
      "name": "Vibrava",
      "image_url": "https://raw.githubusercontent.com/PokeAPI/sprites/master/sprites/pokemon/329.png"
    },
    {
      "id": 330,
      "name": "Flygon",
      "image_url": "https://raw.githubusercontent.com/PokeAPI/sprites/master/sprites/pokemon/330.png"
    }
  ],
  "color": "green",
  "description": "Su medio es el desierto. Para esconderse, levanta arena con las patas. Tiene los ojos protegidos con mallas rojas.",
  "description_catalan": "Aquest Pokémon volador té ales poderoses que li permeten volar amb facilitat."
}