{
  "id": 295,
  "name": "Exploud",
  "height": 15,
  "weight": 840,
  "types": [
    "normal"
  ],
  "image_url": "https://raw.githubusercontent.com/PokeAPI/sprites/master/sprites/pokemon/295.png",
  "stats": {
    "hp": 104,
    "attack": 91,
    "defense": 63,
    "special-attack": 91,
    "special-defense": 73,
    "speed": 68
  },
  "evolution": [
    {
      "id": 293,
      "name": "Whismur",
      "image_url": "https://raw.githubusercontent.com/PokeAPI/sprites/master/sprites/pokemon/293.png"
    },
    {
      "id": 294,
      "name": "Loudred",
      "image_url": "https://raw.githubusercontent.com/PokeAPI/sprites/master/sprites/pokemon/294.png"
    },
    {
      "id": 295,
      "name": "Exploud",
      "image_url": "https://raw.githubusercontent.com/PokeAPI/sprites/master/sprites/pokemon/295.png"
    }
  ],
  "color": "blue",
  "description": "Su aullido se puede oír a 10 km. Emite todo tipo de sonidos desde los tubos de su cuerpo.",
  "description_catalan": "Descripció en català per al Pokémon #295. [Traducció pendent]"
}